<annotation>
	<folder>pikacus</folder>
	<filename>31.jpg</filename>
	<path>D:\pikacus\31.jpg</path>
	<source>
		<database>Unknown</database>
	</source>
	<size>
		<width>303</width>
		<height>166</height>
		<depth>3</depth>
	</size>
	<segmented>0</segmented>
	<object>
		<name>pikachu</name>
		<pose>Unspecified</pose>
		<truncated>1</truncated>
		<difficult>0</difficult>
		<bndbox>
			<xmin>1</xmin>
			<ymin>1</ymin>
			<xmax>118</xmax>
			<ymax>145</ymax>
		</bndbox>
	</object>
	<object>
		<name>pikachu</name>
		<pose>Unspecified</pose>
		<truncated>0</truncated>
		<difficult>0</difficult>
		<bndbox>
			<xmin>169</xmin>
			<ymin>103</ymin>
			<xmax>232</xmax>
			<ymax>151</ymax>
		</bndbox>
	</object>
	<object>
		<name>pikachu</name>
		<pose>Unspecified</pose>
		<truncated>0</truncated>
		<difficult>0</difficult>
		<bndbox>
			<xmin>244</xmin>
			<ymin>90</ymin>
			<xmax>295</xmax>
			<ymax>155</ymax>
		</bndbox>
	</object>
</annotation>
